panpy/__init__.py
panpy/pan_sdk/__init__.py
panpy/pan_sdk/stat/__init__.py
panpy/pan_sdk/stat/clean_merged_csv_form_htc_point.py
panpy/pan_sdk/widgets/__init__.py
panpy/pan_sdk/widgets/htc_visualizer.py
panpy-0.0.1.dist-info/LICENSE
panpy-0.0.1.dist-info/METADATA
panpy-0.0.1.dist-info/WHEEL
panpy-0.0.1.dist-info/top_level.txt
panpy-0.0.1.dist-info/RECORD
